launch_concierge/__init__.py
launch_concierge/install.py
launch_concierge/relaunch.py
launch_concierge/concierge_installer/arguments.py
launch_concierge/concierge_installer/functions.py
launch_concierge/concierge_installer/upgrade_scripts.py
launch_concierge/docker_compose/docker-compose-gpu.yml
launch_concierge/docker_compose/docker-compose.yml
launch_concierge/docker_compose/docker_compose_dependencies/docker-compose-concierge.yml
launch_concierge/docker_compose/docker_compose_dependencies/docker-compose-ollama.yml
launch_concierge/docker_compose/docker_compose_dependencies/docker-compose-opensearch.yml
launch_concierge-0.4.0.dist-info/METADATA
launch_concierge-0.4.0.dist-info/WHEEL
launch_concierge-0.4.0.dist-info/entry_points.txt
launch_concierge-0.4.0.dist-info/RECORD
