Metadata-Version: 2.3
Name: launch-concierge
Version: 0.4.0
Requires-Python: >=3.10
Requires-Dist: isi-util
Requires-Dist: packaging
Requires-Dist: script-builder
